Products.BeakerZopeSessionManager-1.0-py3.7-nspkg.pth
Products/BeakerZopeSessionManager/BeakerPermissions.py
Products/BeakerZopeSessionManager/BeakerSessionManager.py
Products/BeakerZopeSessionManager/Interfaces.py
Products/BeakerZopeSessionManager/SessionObject.py
Products/BeakerZopeSessionManager/SessionTraversal.py
Products/BeakerZopeSessionManager/__init__.py
Products.BeakerZopeSessionManager-1.0.dist-info/LICENSE.txt
Products.BeakerZopeSessionManager-1.0.dist-info/METADATA
Products.BeakerZopeSessionManager-1.0.dist-info/WHEEL
Products.BeakerZopeSessionManager-1.0.dist-info/namespace_packages.txt
Products.BeakerZopeSessionManager-1.0.dist-info/top_level.txt
Products.BeakerZopeSessionManager-1.0.dist-info/RECORD
