Metadata-Version: 2.1
Name: Products.BeakerZopeSessionManager
Version: 1.0
Summary: Zope4 session implementation using Beaker
Home-page: https://github.com/gabrielgisoldo/Products.BeakerZopeSessionManager
Author: Gisoldo, Gabriel Diniz
Author-email: gabrielgisoldi@gmail.com
License: MIT
Keywords: zope sessions beaker
Platform: UNKNOWN
Classifier: Programming Language :: Python :: 3
Classifier: License :: OSI Approved :: MIT License
Requires-Python: >=3.7
Requires-Dist: setuptools
Requires-Dist: collective.beaker
Requires-Dist: beaker
Requires-Dist: Zope2
Requires-Dist: zope.interface
